idnow_responses/__init__.py
idnow_responses-0.0.2.dist-info/LICENSE
idnow_responses-0.0.2.dist-info/METADATA
idnow_responses-0.0.2.dist-info/WHEEL
idnow_responses-0.0.2.dist-info/entry_points.txt
idnow_responses-0.0.2.dist-info/top_level.txt
idnow_responses-0.0.2.dist-info/RECORD
